dantzig-0.2.0.dist-info/METADATA
dantzig-0.2.0.dist-info/WHEEL
dantzig-0.2.0.dist-info/license_files/LICENSE
dantzig/exceptions.py
dantzig/model.py
dantzig/optimize.py
dantzig/py.typed
dantzig/__init__.py
dantzig/rust.abi3.so
dantzig-0.2.0.dist-info/RECORD
