Metadata-Version: 2.1
Name: dantzig
Version: 0.2.0
Classifier: Programming Language :: Python :: 3
Classifier: Programming Language :: Rust
Classifier: License :: OSI Approved :: MIT License
Classifier: Operating System :: OS Independent
Classifier: Topic :: Scientific/Engineering :: Mathematics
Classifier: Typing :: Typed
License-File: LICENSE
Summary: A Rust-powered linear programming library for Python.
Author-email: Matteo Santamaria <matteosantama@gmail.com>
Requires-Python: >=3.10
Project-URL: repository, https://github.com/matteosantama/dantzig
